alchemizer/__init__.py
alchemizer/cache.py
alchemizer/entity/__init__.py
alchemizer/session.py
alchemizer-0.1.1.dist-info/LICENSE
alchemizer-0.1.1.dist-info/METADATA
alchemizer-0.1.1.dist-info/WHEEL
alchemizer-0.1.1.dist-info/RECORD
